hamburg/__init__.py
hamburg/exceptions.py
hamburg/hamburg.py
hamburg/models.py
hamburg/py.typed
hamburg-3.0.1.dist-info/LICENSE
hamburg-3.0.1.dist-info/METADATA
hamburg-3.0.1.dist-info/WHEEL
hamburg-3.0.1.dist-info/RECORD
