Metadata-Version: 2.1
Name: hamburg
Version: 3.0.1
Summary: Asynchronous Python client providing Urban Data information of Hamburg
Home-page: https://github.com/klaasnicolaas/python-hamburg
License: MIT
Keywords: urban,data,platform,hamburg,parking,api,async,client
Author: Klaas Schoute
Author-email: hello@student-techlife.com
Maintainer: Klaas Schoute
Maintainer-email: hello@student-techlife.com
Requires-Python: >=3.11,<4.0
Classifier: Framework :: AsyncIO
Classifier: Intended Audience :: Developers
Classifier: License :: OSI Approved :: MIT License
Classifier: Natural Language :: English
Classifier: Programming Language :: Python :: 3
Classifier: Programming Language :: Python :: 3.11
Classifier: Programming Language :: Python :: 3.12
Classifier: Topic :: Software Development :: Libraries :: Python Modules
Requires-Dist: aiohttp (>=3.0.0)
Requires-Dist: pytz (>=2024.1,<2025.0)
Requires-Dist: yarl (>=1.6.0)
Project-URL: Bug Tracker, https://github.com/klaasnicolaas/python-hamburg/issues
Project-URL: Changelog, https://github.com/klaasnicolaas/python-hamburg/releases
Project-URL: Documentation, https://github.com/klaasnicolaas/python-hamburg
Project-URL: Repository, https://github.com/klaasnicolaas/python-hamburg
